zmp_knowledge_store/__init__.py
zmp_knowledge_store/config.py
zmp_knowledge_store/keyword_extractor.py
zmp_knowledge_store/knowledge_store.py
zmp_knowledge_store/qdrant_adapter.py
zmp_knowledge_store/server_main.py
zmp_knowledge_store/utils.py
zmp_knowledge_store_mcp_server-0.4.4.dist-info/LICENSE
zmp_knowledge_store_mcp_server-0.4.4.dist-info/METADATA
zmp_knowledge_store_mcp_server-0.4.4.dist-info/WHEEL
zmp_knowledge_store_mcp_server-0.4.4.dist-info/RECORD
