Metadata-Version: 2.3
Name: zmp-knowledge-store-mcp-server
Version: 0.4.4
Summary: MCP Server for zmp knowledge base
Author: stiron
Author-email: lesch1@gmail.com
Requires-Python: >=3.10,<4.0
Classifier: Programming Language :: Python :: 3
Classifier: Programming Language :: Python :: 3.10
Classifier: Programming Language :: Python :: 3.11
Classifier: Programming Language :: Python :: 3.12
Classifier: Programming Language :: Python :: 3.13
Requires-Dist: accelerate (>=1.7.0,<2.0.0)
Requires-Dist: boto3 (>=1.38.24,<2.0.0)
Requires-Dist: docling (>=2.36.1,<3.0.0)
Requires-Dist: docling-core (>=2.32.0,<3.0.0)
Requires-Dist: fastapi (>=0.110.0,<1.0.0)
Requires-Dist: fastmcp (>=2.6.1,<3.0.0)
Requires-Dist: httpx (>=0.28.1,<0.29.0)
Requires-Dist: huggingface-hub (>=0.32.2,<0.33.0)
Requires-Dist: langchain (>=0.3.25,<0.4.0)
Requires-Dist: llama-index (>=0.12.48,<0.13.0)
Requires-Dist: markdown (>=3.8,<4.0)
Requires-Dist: mcp[cli] (>=1.9.1,<2.0.0)
Requires-Dist: numpy (>=1.21.0,<2.0.0)
Requires-Dist: openai (>=1.88.0,<2.0.0)
Requires-Dist: pdf2image (>=1.17.0,<2.0.0)
Requires-Dist: pillow (>=11.2.1,<12.0.0)
Requires-Dist: protobuf (>=3.20,<4.0)
Requires-Dist: pymupdf (>=1.26.0,<2.0.0)
Requires-Dist: python-dotenv (>=1.1.0,<2.0.0)
Requires-Dist: qdrant-client (<1.14.2)
Requires-Dist: sentence-transformers (>=4.1.0,<5.0.0)
Requires-Dist: torch (>=2.7.0,<3.0.0)
Requires-Dist: transformers (>=4.52.3,<5.0.0)
Requires-Dist: uvicorn (>=0.34.2,<0.35.0)
